libpme.py
__pycache__/libpme.cpython-36.pyc
libpme-1.1.dist-info/DESCRIPTION.rst
libpme-1.1.dist-info/METADATA
libpme-1.1.dist-info/RECORD
libpme-1.1.dist-info/WHEEL
libpme-1.1.dist-info/metadata.json
libpme-1.1.dist-info/top_level.txt
libpme-1.1.dist-info/zip-safe
