Metadata-Version: 2.0
Name: libpme
Version: 1.1
Summary: PNG metadata editor library
Home-page: http://github.com/nilesr/libpme
Author: Niles Rogoff
Author-email: me@niles.xyz
License: UNKNOWN
Platform: UNKNOWN
